django_model_cleanup/__init__.py
django_model_cleanup/errors.py
django_model_cleanup/models.py
django_model_cleanup-0.1.1.dist-info/DESCRIPTION.rst
django_model_cleanup-0.1.1.dist-info/METADATA
django_model_cleanup-0.1.1.dist-info/RECORD
django_model_cleanup-0.1.1.dist-info/WHEEL
django_model_cleanup-0.1.1.dist-info/entry_points.txt
django_model_cleanup-0.1.1.dist-info/metadata.json
django_model_cleanup-0.1.1.dist-info/top_level.txt
