Metadata-Version: 2.0
Name: django-model-cleanup
Version: 0.1.1
Summary: Mixins for model cleanup methods and validation error concatenations
Home-page: https://github.com/wooyek/django-model-cleanup
Author: Janusz Skonieczny
Author-email: js+pypi@bravelabs.pl
License: MIT license
Keywords: django-model-cleanup
Platform: UNKNOWN
Classifier: Development Status :: 3 - Alpha
Classifier: Framework :: Django :: 1.10
Classifier: Intended Audience :: Developers
Classifier: License :: OSI Approved :: MIT License
Classifier: Natural Language :: English
Classifier: Programming Language :: Python :: 2.7
Classifier: Programming Language :: Python :: 3.5
Requires-Python: >=2.7
Requires-Dist: django
Requires-Dist: pathlib
Requires-Dist: Django (>=1.10)
Provides-Extra: factories
Requires-Dist: factory-boy; extra == 'factories'
